<KinBody name="kitchen_drink_bottle">
  <modelsdir>.</modelsdir>     <!--for relative path -->
  <Body type="dynamic">
    <Geom type="trimesh">
      <Data>../objects//Objects_in_kitchen/drinkbottle.ply 0.002</Data>
      <Render>../objects//Objects_in_kitchen/drinkbottle.ply 0.002</Render>
      <Collision>../objects//Objects_in_kitchen/drinkbottle.ply 0.002</Collision>
      <transparency>0</transparency>
      <DiffuseColor>0.254902 0.411765 0.882353 </DiffuseColor>>
      <RotationAxis>1 0 0 90</RotationAxis>
      <Translation>0 0 0.2</Translation>


    </Geom>      
  </Body>
</KinBody>
